faculty_sync/__init__.py
faculty_sync/app.py
faculty_sync/controller.py
faculty_sync/dirs.py
faculty_sync/file_trees.py
faculty_sync/logs.py
faculty_sync/models.py
faculty_sync/path_match.py
faculty_sync/pubsub.py
faculty_sync/ssh.py
faculty_sync/sync.py
faculty_sync/ui.py
faculty_sync/update.py
faculty_sync/version.py
faculty_sync/watch_sync.py
faculty_sync/cli/__init__.py
faculty_sync/cli/config.py
faculty_sync/cli/models.py
faculty_sync/cli/projects.py
faculty_sync/cli/servers.py
faculty_sync/cli/tests/__init__.py
faculty_sync/cli/tests/test_cli.py
faculty_sync/cli/tests/test_config.py
faculty_sync/screens/__init__.py
faculty_sync/screens/base.py
faculty_sync/screens/choose_remote_dir.py
faculty_sync/screens/diff.py
faculty_sync/screens/help.py
faculty_sync/screens/humanize.py
faculty_sync/screens/loading.py
faculty_sync/screens/sync.py
faculty_sync/screens/walking_trees.py
faculty_sync/screens/watch_sync.py
faculty_sync/screens/components/__init__.py
faculty_sync/screens/components/table.py
faculty_sync/screens/components/vertical_menu.py
faculty_sync/screens/components/tests/__init__.py
faculty_sync/screens/components/tests/test_table.py
faculty_sync/screens/components/tests/test_vertical_menu.py
faculty_sync/tests/__init__.py
faculty_sync/tests/test_path_match.py
faculty_sync-0.4.1.dist-info/LICENSE.txt
faculty_sync-0.4.1.dist-info/METADATA
faculty_sync-0.4.1.dist-info/WHEEL
faculty_sync-0.4.1.dist-info/entry_points.txt
faculty_sync-0.4.1.dist-info/top_level.txt
faculty_sync-0.4.1.dist-info/RECORD
